app_settings_dict/__init__.py
app_settings_dict/app_settings_dict.py
app_settings_dict/defaults_dict.py
app_settings_dict/py.typed
app_settings_dict-0.6.4.dist-info/LICENSE
app_settings_dict-0.6.4.dist-info/METADATA
app_settings_dict-0.6.4.dist-info/WHEEL
app_settings_dict-0.6.4.dist-info/top_level.txt
app_settings_dict-0.6.4.dist-info/RECORD
