Metadata-Version: 2.1
Name: app-settings-dict
Version: 0.6.4
Summary: A dictionary to manage settings for apps.
Home-page: https://github.com/wheelercj/app_settings
Author: Chris Wheeler
Author-email: christopher.wheeler.320@my.csun.edu
License: MIT
Platform: unix
Platform: linux
Platform: osx
Platform: cygwin
Platform: win32
Classifier: Programming Language :: Python :: 3 :: Only
Classifier: Programming Language :: Python :: 3
Classifier: Programming Language :: Python :: 3.7
Classifier: Programming Language :: Python :: 3.8
Classifier: Programming Language :: Python :: 3.9
Classifier: Programming Language :: Python :: 3.10
Requires-Python: >=3.7
License-File: LICENSE
Requires-Dist: typing-extensions
